django_extra_cbv-0.2.1.dist-info/METADATA
django_extra_cbv-0.2.1.dist-info/RECORD
django_extra_cbv-0.2.1.dist-info/WHEEL
django_extra_cbv-0.2.1.dist-info/top_level.txt
extra_cbv/__init__.py
extra_cbv/context_processors.py
extra_cbv/decorators.py
extra_cbv/serializers.py
extra_cbv/utils.py
extra_cbv/views/__init__.py
extra_cbv/views/ajax.py
extra_cbv/views/excel.py
extra_cbv/views/form.py
extra_cbv/views/formset.py
extra_cbv/views/inline.py
extra_cbv/views/json.py
extra_cbv/views/mixins.py
extra_cbv/views/rest.py
extra_cbv/views/simple.py
