Metadata-Version: 2.1
Name: django-extra-cbv
Version: 0.2.1
Summary: Extra class based views for Django
Home-page: https://github.com/alekam/django-extra-cbv
Author: Alex Kamedov
Author-email: alex@kamedov.ru
License: New BSD License
Keywords: cbv,class based views
Platform: any
Classifier: Development Status :: 4 - Beta
Classifier: Environment :: Web Environment
Classifier: Framework :: Django
Classifier: Intended Audience :: Developers
Classifier: License :: OSI Approved :: BSD License
Classifier: Operating System :: OS Independent
Classifier: Programming Language :: Python
Classifier: Topic :: Utilities
Requires-Dist: django (<2.0,>=1.9)
